{
  "title": "知乎",
  "domain": "https://www.zhihu.com",
  "loginUrl": "https://www.zhihu.com/#signin",
  "identity": "z_c0",
  "writerUrl": "https://zhuanlan.zhihu.com/write",
  "sleep": 3,
  "fill": [
    {
      "handle": "Js",
      "sleep": 5,
      "js": "document.getElementsByClassName(\"hive-load\")[0].className+=' hide';"
    },
    {
      "handle": "Fill",
      "Selector": "selector",
      "SelectorName": "textarea.Input",
      "Param": "title",
      "sleep": 5
    },
    {
      "handle": "Fill",
      "Selector": "selector",
      "SelectorName": ".public-DraftEditor-content",
      "Param": "content",
      "sleep": 5
    },
    {
      "handle": "Click",
      "Selector": "selector",
      "SelectorName": ".PublishPanel-triggerButton",
      "sleep": 5
    },
    {
      "handle": "Fill",
      "Selector": "selector",
      "SelectorName": "input.preventCloseOnTarget",
      "SelectorVal": "广告",
      "sleep": 5
    },
    {
      "handle": "Click",
      "Selector": "selector",
      "SelectorName": ".publish-suggest li",
      "sleep": 5
    },
    {
      "handle": "Js",
      "js": "document.getElementsByClassName(\"publish-row\")[0].click()",
      "sleep": 5
    },
    {
      "handle": "Click",
      "Selector": "selector",
      "SelectorName": ".publish-button",
      "sleep": 5
    },
    {
      "handle": "Click",
      "Selector": "selector",
      "SelectorName": ".publish-columnLabel-0",
      "sleep": 5
    },
    {
      "handle": "Click",
      "Selector": "selector",
      "SelectorName": ".publish-stepTwoButton",
      "sleep": 5
    },
    {
      "handle": "Text",
      "Selector": "selector",
      "SelectorName": ".PostComment-orgTab .Tab button",
      "sleep": 3,
      "result": "还没有评论"
    }
  ]
}